{
  "locale": "fr_FR",
  "languageName": "Français",
  "strings": {
    "search.placeholder": "Chercher une règle...",
    "search.label": "Chercher une règle",
    "search.clear": "Effacer la recherche",
    "sections.favorites.title": "Favoris",
    "sections.favorites.subtitle": "Tes règles rapides (glisse ou Shift+Flèche pour réordonner)",
    "sections.favorites.empty": "Clique sur l’étoile d’une règle pour l’ajouter à tes favoris.",
    "sections.movement.title": "Déplacement",
    "sections.movement.subtitle": "limité par ta vitesse",
    "sections.movement.description": "Tu peux te déplacer à tout moment pendant ton tour, avant, après ou entre tes actions.",
    "sections.action.title": "Action",
    "sections.action.subtitle": "1/tour",
    "sections.action.description": "Tu peux aussi interagir gratuitement avec un objet ou un élément de l’environnement.",
    "sections.bonusAction.title": "Action bonus",
    "sections.bonusAction.subtitle": "max. 1/tour",
    "sections.bonusAction.description": "Tu ne peux faire une action bonus que si une capacité, un sort ou une aptitude te le permet.",
    "sections.reaction.title": "Réaction",
    "sections.reaction.subtitle": "max. 1/round",
    "sections.reaction.description": "Une réaction est une réponse instantanée à un déclencheur précis, pendant ton tour ou celui de quelqu’un d’autre.",
    "sections.condition.title": "État",
    "sections.condition.description": "Les états changent tes capacités de différentes façons, souvent à cause d’un sort, d’une aptitude de classe, d’une attaque de monstre ou d’un autre effet.",
    "sections.environment.title": "Effets d’environnement",
    "sections.environment.obscurance": "Les effets qui gênent la vision peuvent compliquer beaucoup d’activités d’aventure.",
    "sections.environment.light": "La présence ou l’absence de lumière crée trois catégories d’éclairage.",
    "sections.environment.vision": "Certaines créatures ont des sens spéciaux pour percevoir leur environnement.",
    "sections.environment.cover": "Les obstacles peuvent donner un abri en combat et rendre une cible plus difficile à blesser.",
    "sections.environment.other": "Les aventuriers peuvent aussi tomber sur des dangers environnementaux et des menaces cachées.",
    "settings.title": "Réglages & accessibilité",
    "settings.content.title": "Rulesets de contenu",
    "settings.content.description": "Choisis quels rulesets sont affichés dans l’appli.",
    "settings.optional.title": "Afficher les règles optionnelles (*)",
    "settings.optional.description": "Afficher ou masquer les règles optionnelles du DMG.",
    "settings.homebrew.title": "Afficher les règles homebrew (**)",
    "settings.homebrew.description": "Afficher ou masquer les règles homebrew les plus courantes.",
    "settings.rules2024.title": "Utiliser les règles 2024",
    "settings.rules2024.description": "Active les règles D&D 2024.",
    "settings.appearance.title": "Apparence & accessibilité",
    "settings.appearance.description": "Ajuste l’apparence et le comportement de l’appli.",
    "settings.language.title": "Langue",
    "settings.language.description": "Choisis la langue du menu et des règles.",
    "settings.theme.title": "Thème de couleur",
    "settings.theme.description": "Change l’apparence de l’appli.",
    "settings.darkMode.title": "Mode sombre",
    "settings.darkMode.description": "Passe du mode clair au mode sombre.",
    "settings.reduceMotion.title": "Réduire les animations",
    "settings.reduceMotion.description": "Désactive les animations et transitions.",
    "settings.wakeLock.title": "Garder l’écran allumé",
    "settings.wakeLock.description": "Empêche l’écran de se mettre en veille pendant l’utilisation.",
    "settings.density.title": "Densité d’affichage",
    "settings.density.description": "Ajuste l’espacement et la taille des éléments.",
    "settings.data.title": "Gestion des données",
    "settings.exportNotes.title": "Exporter les notes",
    "settings.exportNotes.description": "Télécharge tes notes (JSON compressé).",
    "settings.importNotes.title": "Importer des notes",
    "settings.importNotes.description": "Restaure des notes depuis un ancien fichier d’export.",
    "settings.importNotes.fileLabel": "Fichier de notes à importer",
    "settings.exportFavorites.title": "Exporter les favoris",
    "settings.exportFavorites.description": "Télécharge ta liste de favoris (JSON).",
    "footer.github": "Voir sur GitHub",
    "footer.message": "Un outil de référence rapide pour les joueurs et MJ de Dungeons & Dragons 5e.",
    "footer.readme": "README",
    "footer.reportRule": "Signaler une règle manquante ou incorrecte",
    "footer.otherTools": "Autres outils",
    "footer.gmTools": "Lié au GM/DM",
    "footer.mapMakers": "Créateurs de cartes",
    "footer.forPlaying": "Pour jouer",
    "cookie.title": "Ta confidentialité",
    "cookie.text": "Ce site utilise le stockage local pour enregistrer tes préférences et réglages. En cliquant sur \"Accepter\", tu acceptes cette pratique.",
    "cookie.remindLater": "Me le rappeler plus tard",
    "cookie.accept": "Accepter",
    "buttons.closeAllPopups": "Fermer tous les popups",
    "buttons.shortcuts": "Raccourcis clavier",
    "buttons.backToTop": "Retour en haut"
  }
}
